{
  "$schema": "http://json-schema.org/draft-07/schema#",
  "type": "object",
  "properties": {
    "connect": {
      "type": "object",
      "properties": {
        "enabled": { "type": "boolean" },
        "replicas": { "type": "integer", "minimum": 0 },
        "image": {
          "type": "object",
          "properties": {
            "repository": { "type": "string" },
            "tag": { "type": "string" }
          }
        }
      }
    },
    "rbac": {
      "type": "object",
      "properties": {
        "create": { "type": "boolean" }
      }
    }
  }
}
